InstMem.v
// Instruction memory

module InstMem(clock, addr, inst);
  input clock;
  input [31:0] addr;

  output reg [31:0] inst;

  // Stores a 128 array of 32-bit instructions
  reg [31:0] Mem [0:127];

  integer i;

  initial begin
    for(i = 0; i < 127; i = i + 1) begin
      Mem[i] = 0;
    end

    $display("[DEBUG] Reading instructions from Instruction.txt");
    
    // Syntax for readmemh
    // $readmemh("hex_memory_file.mem", memory_array, [start_address], [end_address])
    $readmemh("Instruction.txt", Mem);
    
    // Debug
    for(i = 0; i < 127; i = i + 1)
      $display("[DEBUG] InstMem[%d] -> HEX:%h BINARY:%b, %b, %b, %b, %b, %b, %b", i, Mem[i], Mem[i], Mem[i][31:26], Mem[i][25:21], Mem[i][20:16], Mem[i][15:11], Mem[i][10:6], Mem[i][5:0]);
  end

  always @(posedge clock) begin
    inst <= Mem[addr[31:2]];
  end
endmodule

tb_InstMem/tb_InstMem.v
`timescale 1ns / 1ps

module InstMem_tb;

  // Inputs
  reg clock;
  reg [31:0] addr;

  // Outputs
  wire [31:0] inst;

  // Instantiate the Unit Under Test (UUT)
  InstMem uut (
    .clock(clock), 
    .addr(addr), 
    .inst(inst)
  );

  // Clock generation
  initial begin
    clock = 0;
    forever #10 clock = ~clock; // Toggle clock every 10 ns
  end

  initial begin
    // Initialize Inputs
    addr = 0;

    // Wait for global reset
    #100;
    
    // Test Case 1: Read instruction at address 0
    addr = 0; // Address 0 corresponds to Mem[0]
    #20; // Wait for two clock cycles

    // Test Case 2: Read instruction at address 4
    addr = 4; // Address 4 corresponds to Mem[1] due to word alignment (addr[31:2])
    #20;

    // Test Case 3: Read instruction at address 8
    addr = 8; // Address 8 corresponds to Mem[2]
    #20;

    // Test Case 4: Read instruction at address 12
    addr = 12; // Address 12 corresponds to Mem[3]
    #20;

    // Finish the simulation
    $finish;
  end
  
  // Monitor changes and display
  initial begin
    $dumpfile("tb_InstMem/tb_inst_mem.vcd");
    $dumpvars(0, InstMem_tb);
    $monitor("At time %t, Address = %h, Instruction = %h",
              $time, addr, inst);
  end

endmodule

tb_InstMem/tb_inst_mem.vcd
$date
	Thu Dec 21 19:52:02 2023
$end
$version
	Icarus Verilog
$end
$timescale
	1ps
$end
$scope module InstMem_tb $end
$var wire 32 ! inst [31:0] $end
$var reg 32 " addr [31:0] $end
$var reg 1 # clock $end
$scope module uut $end
$var wire 32 $ addr [31:0] $end
$var wire 1 # clock $end
$var reg 32 % inst [31:0] $end
$var integer 32 & i [31:0] $end
$upscope $end
$upscope $end
$enddefinitions $end
$comment Show the parameter values. $end
$dumpall
$end
#0
$dumpvars
b100 &
bx %
b0 $
0#
b0 "
bx !
$end
#10000
b1000100001100000100000 !
b1000100001100000100000 %
1#
#20000
0#
#30000
1#
#40000
0#
#50000
1#
#60000
0#
#70000
1#
#80000
0#
#90000
1#
#100000
0#
#110000
1#
#120000
0#
b100 "
b100 $
#130000
b10101100000000010000000000000000 !
b10101100000000010000000000000000 %
1#
#140000
0#
b1000 "
b1000 $
#150000
b10001100001001000000000000000000 !
b10001100001001000000000000000000 %
1#
#160000
0#
b1100 "
b1100 $
#170000
b10000001000010000000000000001 !
b10000001000010000000000000001 %
1#
