PC.v
module PC (
  clock, reset,
  PCin, PCout
);
  // PC - program counter

  input wire clock, reset;
  input wire [31:0] PCin;

  output reg [31:0] PCout;

  // Initialize the PC to zero or a specific starting address
  initial PCout = 32'h00000000;

 always @(posedge clock or posedge reset) begin
    if (reset) begin
      // Reset PC to the starting address
      PCout <= 32'h00000000;
    end else begin
      // Update PC to PCin or increment by 4
      // This assumes that PCin is appropriately set by the controlling logic

      // #2; // delay 2 time units
      // PCout <= PCin + 4;
      PCout <= PCin;
    end
  end
      
  /*
  Why do we add 4?

  The program counter or PC register holds the address of the current instruction. MIPS instructions are each four bytes long, so the PC should be incremented by four to read the next instruction in sequence.

  4 bytes (1 byte = 8 bits) => 4 * 8 = 32 bits
  */
endmodule

tb_PC/tb_PC.v
`timescale 1ns / 1ps

module PC_tb;

  // Inputs
  reg clock;
  reg reset;
  reg [31:0] PCin;

  // Outputs
  wire [31:0] PCout;

  // Instantiate the Unit Under Test (UUT)
  PC uut (
    .clock(clock), 
    .reset(reset), 
    .PCin(PCin), 
    .PCout(PCout)
  );

  // Clock generation
  initial begin
    clock = 0;
    forever #10 clock = ~clock; // Generate a clock with period 20ns
  end

  initial begin
    // Initialize Inputs
    reset = 1;
    PCin = 0;

    // Wait for global reset
    #100;
    
    // Release the reset and set initial PC value
    reset = 0;
    PCin = 32'h00000000; // Start from address 0
    #20;

    // Check PC incrementing
    PCin = PCout; // Should increment by 4 each cycle
    #20;
    PCin = PCout;
    #20;
    PCin = PCout;
    #20;

    // Test the reset functionality
    reset = 1; // Assert reset
    #20;
    reset = 0; // Deassert reset
    PCin = 32'h00000020; // Set a different start address
    #20;

    // Check if PC increments from the new value
    PCin = PCout;
    #20;
    PCin = PCout;
    #20;

    // Finish the simulation
    $finish;
  end
  
  // Monitor changes and display
  initial begin
    $dumpfile("tb_PC/tb_pc.vcd");
    $dumpvars(0, PC_tb);
    $monitor("At time %t, Reset = %b, PCin = %h, PCout = %h",
              $time, reset, PCin, PCout);
  end

endmodule

tb_PC/tb_pc.vcd
$date
	Thu Dec 21 23:21:37 2023
$end
$version
	Icarus Verilog
$end
$timescale
	1ps
$end
$scope module PC_tb $end
$var wire 32 ! PCout [31:0] $end
$var reg 32 " PCin [31:0] $end
$var reg 1 # clock $end
$var reg 1 $ reset $end
$scope module uut $end
$var wire 32 % PCin [31:0] $end
$var wire 1 # clock $end
$var wire 1 $ reset $end
$var reg 32 & PCout [31:0] $end
$upscope $end
$upscope $end
$enddefinitions $end
$comment Show the parameter values. $end
$dumpall
$end
#0
$dumpvars
bx &
b0 %
1$
0#
b0 "
bx !
$end
#10000
b0 !
b0 &
1#
#20000
0#
#30000
1#
#40000
0#
#50000
1#
#60000
0#
#70000
1#
#80000
0#
#90000
1#
#100000
0#
0$
#110000
b100 !
b100 &
1#
#120000
0#
b100 "
b100 %
#130000
b1000 !
b1000 &
1#
#140000
0#
b1000 "
b1000 %
#150000
b1100 !
b1100 &
1#
#160000
0#
b1100 "
b1100 %
#170000
b10000 !
b10000 &
1#
#180000
0#
1$
#190000
b0 !
b0 &
1#
#200000
0#
b100000 "
b100000 %
0$
#210000
b100100 !
b100100 &
1#
#220000
0#
b100100 "
b100100 %
#230000
b101000 !
b101000 &
1#
#240000
0#
b101000 "
b101000 %
#250000
b101100 !
b101100 &
1#
